{
    "name": "demo_example",
    "parameters": {},
    "type": "stack_infrastructure_template",
    "environment": ["example"],
    "location": ["vmw_example"],
    "zone": ["example_user"],
    "infrastructure_targets": ["example.vmw_example.example_user"],
    "infrastructure_capabilities": {
        "example.vmw_example.example_user": {
            "description": "The VMware of Example",
            "type": "zone",
            "name": "example_user",
            "hostname": "https://p00vca01.nubera.local",
            "username": "administrator@vsphere.local",
            "password": "PASSWORD!",
            "folder": "fred_10.10.3.0",
            "datacenter": "DC01",
            "cluster": "CL01"
        }
    },
    "description": "SIT updated at 2019-12-01 19h07m23s",
    "subcategory": "SIT",
    "category": "configs"
}